Teleios/GEMLib.py
Teleios/_GEMLib.so
Teleios/__init__.py
GEMLibrary_linux-0.3.2.dist-info/METADATA
GEMLibrary_linux-0.3.2.dist-info/WHEEL
GEMLibrary_linux-0.3.2.dist-info/top_level.txt
GEMLibrary_linux-0.3.2.dist-info/RECORD
