Metadata-Version: 2.1
Name: GEMLibrary-linux
Version: 0.3.2
Summary: Derivatives Library for Teleios
Home-page: UNKNOWN
Author: Kevin Morgan
License: UNKNOWN
Platform: UNKNOWN
Classifier: Programming Language :: Python :: 3.7
Classifier: License :: Other/Proprietary License
Classifier: Operating System :: POSIX :: Linux
Requires-Python: >=3.7
